{
  "name": null,
  "map": "Douze",
  "pos_x": 28,
  "pos_y": -12,
  "web_text": "<p><span style=\"color: #FFFF00\">Equipez</span> la <span style=\"color: #FFFF00\">Panoplie du Wa</span><span style=\"color: #FFFFFF\">.</span></p><p></p><p>Parlez <span style=\"color: #FFFFFF\">au </span><span style=\"color: #FFFF00\">Gawde Wabbit</span><span style=\"color: #FFFFFF\"> pour </span><span style=\"color: #FFFF00\">effectuez </span><span style=\"color: #FFFFFF\">le donjon </span><span data-type=\"custom-tag\" data-id=\"17\" class=\"tag-dungeon\" id=\"13\" type=\"dungeon\" name=\"Terrier du Wa Wabbit\" imageurl=\"https://ganymede-dofus.com/images/icon_dungeon.png\" dofusdbid=\"17\"><img src=\"https://ganymede-dofus.com/images/icon_dungeon.png\" alt=\"dungeon\"><span>Terrier du Wa Wabbit</span></span>.</p><p></p><p><span style=\"color: #FA0000\">Attention ne sortez pas à la fin !</span></p><p></p><p><span style=\"color: #05A045\">Astuces :</span></p><p>- Vous pouvez <span style=\"color: #FFFF00\">retirer</span> la <span style=\"color: #FFFF00\">Panoplie du Wa</span> pendant le <span style=\"color: #FFFF00\">donjon</span>.</p><p>- Avancez dans le <span style=\"color: #FFFF00\">succès monstre Gawde du Wa</span><span style=\"color: #FFFFFF\">.</span></p><p><span style=\"color: #FFFFFF\">- Si vous voulez faire le </span><span data-type=\"custom-tag\" data-id=\"737\" class=\"tag-item\" id=\"344\" type=\"item\" name=\"Dofus Émeraude\" imageurl=\"https://api.dofusdb.fr/img/items/23002.png\" dofusdbid=\"737\"><img src=\"https://api.dofusdb.fr/img/items/23002.png\" alt=\"item\"><span>Dofus Émeraude</span></span> vous devrez <span style=\"color: #FFFF00\">capturer </span>ce <span style=\"color: #FFFF00\">boss</span>.</p><p></p><p>Après avoir vaincu le<span data-type=\"custom-tag\" data-id=\"3460\" class=\"tag-monster\" id=\"1504\" type=\"monster\" name=\"Wa Wobot\" imageurl=\"https://api.dofusdb.fr/img/monsters/3460.png\" dofusdbid=\"3460\"><img src=\"https://api.dofusdb.fr/img/monsters/3460.png\" alt=\"monster\"><span>Wa Wobot</span></span>, <span style=\"color: #FFFF00\">équipez</span> la <span style=\"color: #FFFF00\">Panoplie du Wa</span>.</p><p></p><p><span style=\"color: #FFFF00\">Parlez </span>au <span style=\"color: #FFFF00\">Gawdien du Dofus</span><span style=\"color: #FFFFFF\"> pour prendre le </span><span data-type=\"custom-tag\" data-id=\"972\" class=\"tag-item\" id=\"502\" type=\"item\" name=\"Dofus Cawotte\" imageurl=\"https://api.dofusdb.fr/img/items/23006.png\" dofusdbid=\"972\"><img src=\"https://api.dofusdb.fr/img/items/23006.png\" alt=\"item\"><span>Dofus Cawotte</span></span>.</p><p></p><p><span style=\"color: #FFFF00\">Utilisez </span>1 <span data-type=\"custom-tag\" data-id=\"548\" class=\"tag-item\" id=\"267\" type=\"item\" name=\"Potion de Rappel\" imageurl=\"https://api.dofusdb.fr/img/items/12017.png\" dofusdbid=\"548\"><img src=\"https://api.dofusdb.fr/img/items/12017.png\" alt=\"item\"><span>Potion de Rappel</span></span> pour vous téléporter au Zaap.</p><p></p><p>Ensuite <span style=\"color: #62ACFF\">allez en</span> [23,-4]</p><p></p><ul data-type=\"taskList\"><li data-checked=\"false\" data-type=\"taskItem\"><label><input type=\"checkbox\"><span></span></label><div><p><span style=\"color: #62ACFF\">2 maps à gauche</span></p></div></li></ul>"
}
